cellrake/__init__.py
cellrake/main.py
cellrake/predicting.py
cellrake/segmentation.py
cellrake/training.py
cellrake/utils.py
cellrake-0.3.0.dist-info/METADATA
cellrake-0.3.0.dist-info/WHEEL
cellrake-0.3.0.dist-info/licenses/LICENSE
cellrake-0.3.0.dist-info/RECORD
