Metadata-Version: 2.4
Name: cellrake
Version: 0.3.0
Summary: A Python package for analyzing cells in fluorescent images
Project-URL: Homepage, https://github.com/marccanela/cellrake
Author-email: Marc Canela <marc.canela@outlook.com>
License-Expression: MIT
License-File: LICENSE
Keywords: GFP,cFos,colocalization,count cells,fluorescence,image,immunohistochemistry,tdTomato
Classifier: Intended Audience :: Science/Research
Classifier: License :: OSI Approved :: MIT License
Classifier: Operating System :: OS Independent
Classifier: Programming Language :: Python :: 3
Classifier: Topic :: Scientific/Engineering :: Image Processing
Classifier: Topic :: Software Development :: Libraries :: Python Modules
Requires-Python: <3.11,>=3.9
Requires-Dist: matplotlib
Requires-Dist: openpyxl
Requires-Dist: pandas
Requires-Dist: pillow
Requires-Dist: scikit-image
Requires-Dist: scikit-learn
Requires-Dist: scipy
Requires-Dist: shapely
Requires-Dist: tqdm
Provides-Extra: dev
Requires-Dist: black; extra == 'dev'
Requires-Dist: pytest; extra == 'dev'
